b_continuous_subprocess/__init__.py
b_continuous_subprocess/continuous_subprocess.py
b_continuous_subprocess_test/tests/__init__.py
b_continuous_subprocess_test/tests/test_subprocess_error.py
b_continuous_subprocess_test/tests/test_subprocess_output.py
b_continuous_subprocess-0.4.0.dist-info/LICENSE
b_continuous_subprocess-0.4.0.dist-info/METADATA
b_continuous_subprocess-0.4.0.dist-info/WHEEL
b_continuous_subprocess-0.4.0.dist-info/top_level.txt
b_continuous_subprocess-0.4.0.dist-info/RECORD
