Metadata-Version: 2.1
Name: b-continuous-subprocess
Version: 0.4.0
Summary: Allows to execute subprocess commands and get their output in real-time.
Home-page: https://github.com/biomapas/B.ContinuousSubprocess.git
Author: Laimonas Sutkus
Author-email: laimonas.sutkus@biomapas.com
License: Apache License 2.0
Keywords: Subprocess
Classifier: Programming Language :: Python :: 3
Classifier: Operating System :: OS Independent
License-File: LICENSE
